pbasemap/__init__.py
pbasemap/__main__.py
pbasemap/geom_rbox.py
pbasemap/mos_download.py
pbasemap/mos_pydl.py
pbasemap/mosaic_metadata.py
pbasemap/pbasemap.py
pbasemap/shp2geojson.py
pbasemap-0.1.0.dist-info/METADATA
pbasemap-0.1.0.dist-info/RECORD
pbasemap-0.1.0.dist-info/WHEEL
pbasemap-0.1.0.dist-info/entry_points.txt
pbasemap-0.1.0.dist-info/top_level.txt
