Metadata-Version: 2.1
Name: pbasemap
Version: 0.1.0
Summary: Tool to download Planet Monthly Mosaic Quads
Home-page: https://github.com/samapriya/Planet-Mosaic-Quads-Download-CLI
Author: Samapriya Roy
Author-email: samapriya.roy@gmail.com
License: Apache 2.0
Platform: UNKNOWN
Classifier: Development Status :: 3 - Alpha
Classifier: Intended Audience :: Developers
Classifier: Intended Audience :: Science/Research
Classifier: Natural Language :: English
Classifier: License :: OSI Approved :: Apache Software License
Classifier: Programming Language :: Python
Classifier: Programming Language :: Python :: 2.7
Classifier: Programming Language :: Python :: 3.6
Classifier: Operating System :: OS Independent
Classifier: Topic :: Scientific/Engineering :: GIS
Requires-Dist: requests (>=2.19.1)
Requires-Dist: DateTimeRange (>=0.5.5)
Requires-Dist: planet (>=1.2.1)
Requires-Dist: psutil (>=5.4.5)
Requires-Dist: retrying (>=1.3.3)
Requires-Dist: shapely; platform_system != "Windows"
Requires-Dist: geopandas (>=0.4.0); platform_system != "Windows"
Requires-Dist: fiona (>=1.8.6); platform_system != "Windows"
Requires-Dist: pypiwin32; platform_system == "Windows"
Requires-Dist: pywin32; platform_system == "Windows"
Requires-Dist: pySmartDL (==1.2.5); python_version < "3.4"
Requires-Dist: pySmartDL (>=1.3.1); python_version > "3.4"
